[
  {
    "name": "Pressure",
    "description": "Resource pressure via PSI",
    "query": "irate(node_pressure_cpu_waiting_seconds_total[30m])",
    "metrics": [
      "node_pressure_cpu_waiting_seconds_total"
    ]
  },
  {
    "name": "Pressure",
    "description": "Resource pressure via PSI",
    "query": "irate(node_pressure_memory_waiting_seconds_total[30m])",
    "metrics": [
      "node_pressure_memory_waiting_seconds_total"
    ]
  },
  {
    "name": "Pressure",
    "description": "Resource pressure via PSI",
    "query": "irate(node_pressure_io_waiting_seconds_total[30m])",
    "metrics": [
      "node_pressure_io_waiting_seconds_total"
    ]
  },
  {
    "name": "CPU Busy",
    "description": "Busy state of all CPU cores together",
    "query": "100 * (1 - avg(rate(node_cpu_seconds_total[30m])))",
    "metrics": [
      "node_cpu_seconds_total"
    ]
  },
  {
    "name": "RAM Used",
    "description": "Non available RAM memory",
    "query": "((node_memory_MemTotal_bytes - node_memory_MemFree_bytes) / node_memory_MemTotal_bytes) * 100",
    "metrics": [
      "node_memory_MemFree_bytes",
      "node_memory_MemTotal_bytes"
    ]
  },
  {
    "name": "RAM Used",
    "description": "Non available RAM memory",
    "query": "(1 - (node_memory_MemAvailable_bytes / node_memory_MemTotal_bytes)) * 100",
    "metrics": [
      "node_memory_MemAvailable_bytes",
      "node_memory_MemTotal_bytes"
    ]
  },
  {
    "name": "SWAP Used",
    "description": "Used Swap",
    "query": "((node_memory_SwapTotal_bytes - node_memory_SwapFree_bytes) / (node_memory_SwapTotal_bytes)) * 100",
    "metrics": [
      "node_memory_SwapFree_bytes",
      "node_memory_SwapTotal_bytes"
    ]
  },
  {
    "name": "Root FS Used",
    "description": "Used Root FS",
    "query": "100 - ((node_filesystem_avail_bytes * 100) / node_filesystem_size_bytes)",
    "metrics": [
      "node_filesystem_avail_bytes",
      "node_filesystem_size_bytes"
    ]
  },
  {
    "name": "Uptime",
    "description": "System uptime",
    "query": "node_time_seconds - node_boot_time_seconds",
    "metrics": [
      "node_boot_time_seconds",
      "node_time_seconds"
    ]
  },
  {
    "name": "RootFS Total",
    "description": "Total RootFS",
    "query": "node_filesystem_size_bytes",
    "metrics": [
      "node_filesystem_size_bytes"
    ]
  },
  {
    "name": "RAM Total",
    "description": "Total RAM",
    "query": "node_memory_MemTotal_bytes",
    "metrics": [
      "node_memory_MemTotal_bytes"
    ]
  },
  {
    "name": "SWAP Total",
    "description": "Total SWAP",
    "query": "node_memory_SwapTotal_bytes",
    "metrics": [
      "node_memory_SwapTotal_bytes"
    ]
  },
  {
    "name": "Memory Basic",
    "description": "Basic memory usage",
    "query": "node_memory_MemTotal_bytes",
    "metrics": [
      "node_memory_MemTotal_bytes"
    ]
  },
  {
    "name": "Memory Basic",
    "description": "Basic memory usage",
    "query": "node_memory_MemTotal_bytes - node_memory_MemFree_bytes - (node_memory_Cached_bytes + node_memory_Buffers_bytes + node_memory_SReclaimable_bytes)",
    "metrics": [
      "node_memory_Buffers_bytes",
      "node_memory_Cached_bytes",
      "node_memory_MemFree_bytes",
      "node_memory_MemTotal_bytes",
      "node_memory_SReclaimable_bytes"
    ]
  },
  {
    "name": "Memory Basic",
    "description": "Basic memory usage",
    "query": "node_memory_Cached_bytes + node_memory_Buffers_bytes + node_memory_SReclaimable_bytes",
    "metrics": [
      "node_memory_Buffers_bytes",
      "node_memory_Cached_bytes",
      "node_memory_SReclaimable_bytes"
    ]
  },
  {
    "name": "Memory Basic",
    "description": "Basic memory usage",
    "query": "node_memory_MemFree_bytes",
    "metrics": [
      "node_memory_MemFree_bytes"
    ]
  },
  {
    "name": "Memory Basic",
    "description": "Basic memory usage",
    "query": "(node_memory_SwapTotal_bytes - node_memory_SwapFree_bytes)",
    "metrics": [
      "node_memory_SwapFree_bytes",
      "node_memory_SwapTotal_bytes"
    ]
  },
  {
    "name": "Network Traffic Basic",
    "description": "Basic network info per interface",
    "query": "irate(node_network_receive_bytes_total[30m])*8",
    "metrics": [
      "node_network_receive_bytes_total"
    ]
  },
  {
    "name": "Network Traffic Basic",
    "description": "Basic network info per interface",
    "query": "irate(node_network_transmit_bytes_total[30m])*8",
    "metrics": [
      "node_network_transmit_bytes_total"
    ]
  },
  {
    "name": "Disk Space Used Basic",
    "description": "Disk space used of all filesystems mounted",
    "query": "100 - ((node_filesystem_avail_bytes * 100) / node_filesystem_size_bytes)",
    "metrics": [
      "node_filesystem_avail_bytes",
      "node_filesystem_size_bytes"
    ]
  }
]