[
  {
    "id": "87c51aef-60c1-43b1-b28b-bfc23eac625e",
    "name": "Loki's stored chunk entries",
    "description": "This PromQL query measures the number of stored chunk entries in Loki.",
    "question": "What is the current number of stored chunk entries in Loki?",
    "query": "",
    "metrics": [
      "stored_chunk_entries"
    ]
  },
  {
    "id": "086341ae-e021-438d-a102-7eacefc3a468",
    "name": "Loki's stored chunk entries",
    "description": "This PromQL query measures the number of stored chunk entries in Loki.",
    "question": "How has the number of stored chunk entries in Loki changed over time?",
    "query": "",
    "metrics": [
      "stored_chunk_entries"
    ]
  },
  {
    "id": "b6b047fe-4237-47e5-a072-4072f73cc16e",
    "name": "Loki's stored chunk entries",
    "description": "This PromQL query measures the number of stored chunk entries in Loki.",
    "question": "Are there any anomalies in the number of stored chunk entries in Loki?",
    "query": "",
    "metrics": [
      "stored_chunk_entries"
    ]
  },
  {
    "id": "8b5471e8-dedb-48d5-9735-6a37b2a58423",
    "name": "Average batch appends sent to ingesters (Loki)",
    "description": "This PromQL query measures the average number of batch appends sent to ingesters by the Loki service.",
    "question": "What is the average number of batch appends sent to ingesters by Loki?",
    "query": "",
    "metrics": [
      "batch_appends"
    ]
  },
  {
    "id": "cf37d0d3-3632-4f47-b5bb-a86fa6614825",
    "name": "Average batch appends sent to ingesters (Loki)",
    "description": "This PromQL query measures the average number of batch appends sent to ingesters by the Loki service.",
    "question": "How many batch appends are typically sent to ingesters by Loki?",
    "query": "",
    "metrics": [
      "batch_appends"
    ]
  },
  {
    "id": "26e55526-f23a-4bec-83c2-5fb825b69bc1",
    "name": "Average batch appends sent to ingesters (Loki)",
    "description": "This PromQL query measures the average number of batch appends sent to ingesters by the Loki service.",
    "question": "What is the average rate of batch appends sent to ingesters by Loki?",
    "query": "",
    "metrics": [
      "batch_appends"
    ]
  },
  {
    "id": "24b03a4f-3b91-423d-aea0-fa91b45ea0ea",
    "name": "Number of bytes total by promtail",
    "description": "This PromQL query measures the total number of bytes collected by promtail.",
    "question": "What is the total number of bytes collected by promtail?",
    "query": "",
    "metrics": [
      "promtail"
    ]
  },
  {
    "id": "972b3fde-a994-4f06-b118-0fbe65af4126",
    "name": "Number of bytes total by promtail",
    "description": "This PromQL query measures the total number of bytes collected by promtail.",
    "question": "How many bytes has promtail processed?",
    "query": "",
    "metrics": [
      "promtail"
    ]
  },
  {
    "id": "f04c9c73-9a9c-439a-86e7-feda30312970",
    "name": "Number of bytes total by promtail",
    "description": "This PromQL query measures the total number of bytes collected by promtail.",
    "question": "What is the cumulative count of bytes gathered by promtail?",
    "query": "",
    "metrics": [
      "promtail"
    ]
  },
  {
    "id": "29ceb761-803c-4bb5-b15c-d175291097cb",
    "name": "Number of bytes encoded and ready to send by Promtail",
    "description": "The PromQL query measures the number of bytes that have been encoded and are ready to be sent by Promtail.",
    "question": "What is the total number of bytes encoded by Promtail?",
    "query": "",
    "metrics": [
      "bytes_encoded"
    ]
  },
  {
    "id": "a069d79c-81ff-425d-9658-87765663efc0",
    "name": "Number of bytes encoded and ready to send by Promtail",
    "description": "The PromQL query measures the number of bytes that have been encoded and are ready to be sent by Promtail.",
    "question": "How many bytes are ready to be sent by Promtail?",
    "query": "",
    "metrics": [
      "bytes_encoded"
    ]
  },
  {
    "id": "dccfdf4d-fe56-422f-b915-185fdfda0c1e",
    "name": "Number of bytes encoded and ready to send by Promtail",
    "description": "The PromQL query measures the number of bytes that have been encoded and are ready to be sent by Promtail.",
    "question": "What is the current amount of encoded bytes awaiting transmission by Promtail?",
    "query": "",
    "metrics": [
      "bytes_encoded"
    ]
  }
]