[
  {
    "id": "a1df9703-1df4-43f5-b6c9-83befc5de98d",
    "name": "",
    "description": "This PromQL query measures the rate of a specific metric over a 5-minute window",
    "question": "What is the rate of node_cpu_seconds_total?",
    "query": "",
    "metrics": [
      "node_cpu_seconds_total"
    ]
  },
  {
    "id": "7c0ba8f3-b07f-4481-8f78-f5f614693059",
    "name": "",
    "description": "This PromQL query measures the rate of a specific metric over a 5-minute window",
    "question": "How has the node_cpu_seconds_total metric changed over the past 5 minutes?",
    "query": "",
    "metrics": [
      "node_cpu_seconds_total"
    ]
  },
  {
    "id": "d07b0c12-153d-41aa-8aea-22c485c7f8dd",
    "name": "",
    "description": "This PromQL query measures the rate of a specific metric over a 5-minute window",
    "question": "Which nodes are experiencing the highest node_cpu_seconds_total rate?",
    "query": "",
    "metrics": [
      "node_cpu_seconds_total"
    ]
  },
  {
    "id": "067bc6ff-ef3d-474d-a2f4-7b152284b5e3",
    "name": "",
    "description": "The PromQL query measures the total number of logs generated by services running in Kubernetes over a specified time range.",
    "question": "How many logs have been generated by services in Kubernetes?",
    "query": "",
    "metrics": [
      "logs_total"
    ]
  },
  {
    "id": "8892676b-cac9-4dcf-a3d4-f1ff8ce5221e",
    "name": "",
    "description": "The PromQL query measures the total number of logs generated by services running in Kubernetes over a specified time range.",
    "question": "What is the total count of logs from Kubernetes services?",
    "query": "",
    "metrics": [
      "logs_total"
    ]
  },
  {
    "id": "ff5482cc-6afb-4352-a681-47375029024a",
    "name": "",
    "description": "The PromQL query measures the total number of logs generated by services running in Kubernetes over a specified time range.",
    "question": "Which services in Kubernetes are generating the most logs?",
    "query": "",
    "metrics": [
      "logs_total"
    ]
  }
]