[
  {
    "id": "301d9b9f-b67c-4b0d-856c-8fe6c32c30b7",
    "name": "MySQL Internal Memory Overview",
    "question": "system memory",
    "query": "node_memory_MemTotal_bytes",
    "metrics": [
      "node_memory_MemTotal_bytes"
    ]
  },
  {
    "id": "6abd8274-4d36-48ba-9cbf-704d6bd74d8e",
    "name": "MySQL Internal Memory Overview",
    "question": "innodb buffer pool data",
    "query": "node_memory_MemTotal_bytes",
    "metrics": [
      "node_memory_MemTotal_bytes"
    ]
  },
  {
    "id": "51bf1986-2264-4e0a-8dd9-93a839333923",
    "name": "MySQL Internal Memory Overview",
    "question": "tokudb cache allocation",
    "query": "node_memory_MemTotal_bytes",
    "metrics": [
      "node_memory_MemTotal_bytes"
    ]
  },
  {
    "id": "83804c21-99f3-4ae7-b7d0-a4121fb2221d",
    "name": "I/O Activity",
    "question": "calculate io activity vmstat",
    "query": "rate(node_vmstat_pgpgin[$interval]) * 1024 or irate(node_vmstat_pgpgin[5m]) * 1024",
    "metrics": [
      "node_vmstat_pgpgin"
    ]
  },
  {
    "id": "c2904c52-dc64-497b-8f11-c7f02f11ebf0",
    "name": "I/O Activity",
    "question": "derive inputoutput activity",
    "query": "rate(node_vmstat_pgpgin[$interval]) * 1024 or irate(node_vmstat_pgpgin[5m]) * 1024",
    "metrics": [
      "node_vmstat_pgpgin"
    ]
  },
  {
    "id": "1d447c9d-5949-4498-858c-66860e8f0152",
    "name": "I/O Activity",
    "question": "compute page activity",
    "query": "rate(node_vmstat_pgpgin[$interval]) * 1024 or irate(node_vmstat_pgpgin[5m]) * 1024",
    "metrics": [
      "node_vmstat_pgpgin"
    ]
  },
  {
    "id": "6de691b8-7462-408e-b620-c1440ba8a06e",
    "name": "I/O Activity",
    "question": "io activity node",
    "query": "rate(node_vmstat_pgpgout[$interval]) * 1024 or irate(node_vmstat_pgpgout[5m]) * 1024",
    "metrics": [
      "node_vmstat_pgpgout"
    ]
  },
  {
    "id": "601c56ef-064c-4afe-bce1-11fe25338243",
    "name": "I/O Activity",
    "question": "io activity",
    "query": "rate(node_vmstat_pgpgout[$interval]) * 1024 or irate(node_vmstat_pgpgout[5m]) * 1024",
    "metrics": [
      "node_vmstat_pgpgout"
    ]
  },
  {
    "id": "43b676db-fb62-449a-b45d-412db30ea7b3",
    "name": "I/O Activity",
    "question": "aggregate node io activity trend",
    "query": "rate(node_vmstat_pgpgout[$interval]) * 1024 or irate(node_vmstat_pgpgout[5m]) * 1024",
    "metrics": [
      "node_vmstat_pgpgout"
    ]
  },
  {
    "id": "8abba071-8960-48ae-9ba7-3ee058e7d591",
    "name": "Memory Distribution",
    "question": "memory free distribution node",
    "query": "node_memory_MemFree_bytes",
    "metrics": [
      "node_memory_MemFree_bytes"
    ]
  },
  {
    "id": "43af6441-e75a-4298-b417-fe3f1ae590d2",
    "name": "Memory Distribution",
    "question": "memory available node",
    "query": "node_memory_MemFree_bytes",
    "metrics": [
      "node_memory_MemFree_bytes"
    ]
  },
  {
    "id": "90477187-12f6-45aa-9c81-598d6baf2ee2",
    "name": "Memory Distribution",
    "question": "distribution free memory node",
    "query": "node_memory_MemFree_bytes",
    "metrics": [
      "node_memory_MemFree_bytes"
    ]
  },
  {
    "id": "0fa51f52-d5f8-4aeb-9e14-f8fc405c1327",
    "name": "CPU Usage / Load",
    "question": "cpu load node",
    "query": "node_load1",
    "metrics": [
      "node_load1"
    ]
  },
  {
    "id": "337b19df-c5e1-4e3a-a2aa-d9c36f053f0d",
    "name": "CPU Usage / Load",
    "question": "nodes firstminute load",
    "query": "node_load1",
    "metrics": [
      "node_load1"
    ]
  },
  {
    "id": "0db73f38-36bc-441b-a2ef-669be26529db",
    "name": "CPU Usage / Load",
    "question": "nodes load last minute",
    "query": "node_load1",
    "metrics": [
      "node_load1"
    ]
  },
  {
    "id": "adee46ba-31b5-442e-b219-8aea6991d58b",
    "name": "Swap Activity",
    "question": "swap activity node",
    "query": "rate(node_vmstat_pswpin[$interval]) * 4096 or irate(node_vmstat_pswpin[5m]) * 4096",
    "metrics": [
      "node_vmstat_pswpin"
    ]
  },
  {
    "id": "85134dc0-e930-420b-b455-ce5b499e7bbc",
    "name": "Swap Activity",
    "question": "page swaps into swap space",
    "query": "rate(node_vmstat_pswpin[$interval]) * 4096 or irate(node_vmstat_pswpin[5m]) * 4096",
    "metrics": [
      "node_vmstat_pswpin"
    ]
  },
  {
    "id": "b53c69a1-a22a-42f0-a7b1-8a8a1d1c6267",
    "name": "Swap Activity",
    "question": "swapin activity node",
    "query": "rate(node_vmstat_pswpin[$interval]) * 4096 or irate(node_vmstat_pswpin[5m]) * 4096",
    "metrics": [
      "node_vmstat_pswpin"
    ]
  },
  {
    "id": "bcc8b651-02c3-4aee-9ac7-3fc17aab43c7",
    "name": "Swap Activity",
    "question": "swap out activity",
    "query": "rate(node_vmstat_pswpout[$interval]) * 4096 or irate(node_vmstat_pswpout[5m]) * 4096",
    "metrics": [
      "node_vmstat_pswpout"
    ]
  },
  {
    "id": "8352d845-a4e3-4d0f-abd7-dad85c86a197",
    "name": "Swap Activity",
    "question": "swap out activity interval",
    "query": "rate(node_vmstat_pswpout[$interval]) * 4096 or irate(node_vmstat_pswpout[5m]) * 4096",
    "metrics": [
      "node_vmstat_pswpout"
    ]
  },
  {
    "id": "631ac31a-4676-4106-9186-56dd35894da6",
    "name": "Swap Activity",
    "question": "swap out multiplied 4096",
    "query": "rate(node_vmstat_pswpout[$interval]) * 4096 or irate(node_vmstat_pswpout[5m]) * 4096",
    "metrics": [
      "node_vmstat_pswpout"
    ]
  }
]